pygocron/__init__.py
pygocron/pygocron.py
pygocron-0.2.0.dist-info/LICENSE
pygocron-0.2.0.dist-info/METADATA
pygocron-0.2.0.dist-info/WHEEL
pygocron-0.2.0.dist-info/top_level.txt
pygocron-0.2.0.dist-info/RECORD
