Metadata-Version: 2.1
Name: pygocron
Version: 0.2.0
Summary: python sdk for gocron
Home-page: https://github.com/superjcd/pygocron
Author: Jiang Chaodi
Author-email: 929760274@qq.com
License: MIT license
Keywords: pygocron
Classifier: Development Status :: 2 - Pre-Alpha
Classifier: Intended Audience :: Developers
Classifier: License :: OSI Approved :: MIT License
Classifier: Natural Language :: English
Classifier: Programming Language :: Python :: 3
Classifier: Programming Language :: Python :: 3.6
Classifier: Programming Language :: Python :: 3.7
Classifier: Programming Language :: Python :: 3.8
Requires-Python: >=3.6
License-File: LICENSE
Requires-Dist: requests
